{"active":true,"archived":false,"closed":true,"closedTime":"2022-10-31T04:45:34Z","commentCount":8125,"commentsEnabled":false,"competitive":0,"createdAt":"2022-10-25T18:51:33.745Z","creationDate":"2022-10-25T00:00:00Z","cumulativeMarkets":false,"cyom":false,"deploying":false,"description":"This is a market group for NBA Week 2 games, scheduled to take place over October 24 - 30, 2022.","enableNegRisk":false,"endDate":"2022-10-30T00:00:00Z","featured":false,"icon":"https://polymarket-upload.s3.us-east-2.amazonaws.com/nba.png","id":"834781","image":"https://polymarket-upload.s3.us-east-2.amazonaws.com/nba.png","liquidity":0,"liquidityAmm":0,"liquidityClob":0,"markets":[{"active":true,"approved":true,"archived":false,"bestAsk":1,"bestBid":0,"clearBookOnStart":true,"clobTokenIds":"[\"26775154886451344549558236197850856160174187815049052317007522724434581372007\", \"9463165240109163332180028662596719645154046805982424189000325908579104109523\"]","closed":true,"closedTime":"2022-10-27 19:30:57+00","commentsEnabled":false,"competitive":0,"conditionId":"0xe350924b920bc33b766492a104f24f2dcc81c91d433f6d183000c61924baf18e","createdAt":"2022-10-25T18:55:43.208Z","creator":"","cyom":false,"deploying":false,"description":"In the upcoming NBA game, scheduled for October 26:\n\nIf the Los Angeles Lakers win, the market will resolve to “Lakers”. \n\nIf the Denver Nuggets win, the market will resolve to “Nuggets”. \n\nIf the game is not completed by November 2, 2022 (11:59:59 PM ET), the market will resolve 50-50.","enableOrderBook":false,"endDate":"2022-10-26T00:00:00Z","endDateIso":"2022-10-26","featured":false,"fee":"10000000000000000","feesEnabled":false,"fpmmLive":true,"funded":false,"groupItemThreshold":"2","groupItemTitle":"Wednesday: Lakers vs. Nuggets","hasReviewedDates":true,"holdingRewardsEnabled":false,"icon":"https://polymarket-upload.s3.us-east-2.amazonaws.com/nba.png","id":"247761","image":"https://polymarket-upload.s3.us-east-2.amazonaws.com/nba.png","lastTradePrice":0,"liquidity":"20.005008","liquidityNum":20.01,"manualActivation":false,"marketGroup":608,"marketMakerAddress":"0x6965dd79Cd92b1E587416C1Ce5F8487B1cB116c8","marketType":"normal","negRiskOther":false,"new":false,"oneDayPriceChange":0,"oneHourPriceChange":0,"oneMonthPriceChange":0,"oneWeekPriceChange":0,"oneYearPriceChange":0,"outcomePrices":"[\"0.0000003761323792042673365671999260321589\", \"0.999999623867620795732663432800074\"]","outcomes":"[\"Lakers\", \"Nuggets\"]","pagerDutyNotificationEnabled":false,"pendingDeployment":false,"question":"NBA: Who will win Lakers vs. Nuggets, scheduled for October 26 (10:00 PM ET)?","questionID":"0xb97ba6be3dadaec34aff81f43430949a0a33526a8a59adb2950894aeb6d7f4e7","ready":false,"readyForCron":true,"requiresTranslation":false,"resolutionSource":"https://www.nba.com/games","resolvedBy":"0xCB1822859cEF82Cd2Eb4E6276C7916e692995130","restricted":true,"rewardsMaxSpread":0,"rewardsMinSize":0,"rfqEnabled":false,"secondsDelay":0,"sentDiscord":false,"slug":"nba-who-will-win-lakers-vs-nuggets-scheduled-for-october-26-1000-pm-et","spread":1,"submitted_by":"0x281777D3bdD096d302791F94A2E429bb98474227","umaEndDate":"January 1, 2023","umaEndDateIso":"2023-01-01","umaResolutionStatuses":"[]","updatedAt":"2023-01-31T21:15:18.809Z","updatedBy":15,"volume":"50.008842","volume1mo":0,"volume1moAmm":0,"volume1moClob":0,"volume1wk":0,"volume1wkAmm":0,"volume1wkClob":0,"volume1yr":0,"volume1yrAmm":0,"volume1yrClob":0,"volume24hr":0,"volumeNum":50.01,"wideFormat":true},{"active":true,"approved":true,"archived":false,"bestAsk":1,"bestBid":0,"clearBookOnStart":true,"clobTokenIds":"[\"24778950172524897913731414351208437494561637602332365019339529916250451938115\", \"77551310056301384837649299526603785313594613693495365927043146701124818590379\"]","closed":true,"closedTime":"2022-10-28 09:30:38+00","commentsEnabled":false,"competitive":0,"conditionId":"0x61152ca645aa81833ae2e382dcf15b12742bf5057b91da2485f9325117f0d999","createdAt":"2022-10-25T18:22:09.478Z","creator":"","cyom":false,"deploying":false,"description":"In the upcoming NBA game, scheduled for October 27:\n\nIf the Miami Heat win, the market will resolve to “Heat”. \n\nIf the Golden State Warriors win, the market will resolve to “Warriors”. \n\nIf the game is not completed by November 4, 2022 (11:59:59 PM ET), the market will resolve 50-50.","enableOrderBook":false,"endDate":"2022-10-27T00:00:00Z","endDateIso":"2022-10-27","featured":false,"fee":"10000000000000000","feesEnabled":false,"fpmmLive":true,"funded":false,"groupItemThreshold":"3","groupItemTitle":"Thursday: Heat vs. Warriors","hasReviewedDates":true,"holdingRewardsEnabled":false,"icon":"https://polymarket-upload.s3.us-east-2.amazonaws.com/nba.png","id":"247757","image":"https://polymarket-upload.s3.us-east-2.amazonaws.com/nba.png","lastTradePrice":0,"liquidity":"20.005012","liquidityNum":20.01,"manualActivation":false,"marketGroup":608,"marketMakerAddress":"0xA52b1a27c492b54cc352A4a7d7Cb9A269CC445C5","marketType":"normal","negRiskOther":false,"new":false,"oneDayPriceChange":0,"oneHourPriceChange":0,"oneMonthPriceChange":0,"oneWeekPriceChange":0,"oneYearPriceChange":0,"outcomePrices":"[\"0.000001350146447783058919961339038268755\", \"0.9999986498535522169410800386609617\"]","outcomes":"[\"Heat\", \"Warriors\"]","pagerDutyNotificationEnabled":false,"pendingDeployment":false,"question":"NBA: Who will win Heat vs. Warriors, scheduled for October 27 (10:00 PM ET)?","questionID":"0xed2b2c432cdd4d2a0ef6acaced5205267815c66852a88801845587b189082337","ready":false,"readyForCron":true,"requiresTranslation":false,"resolutionSource":"https://www.nba.com/games","resolvedBy":"0xCB1822859cEF82Cd2Eb4E6276C7916e692995130","restricted":true,"rewardsMaxSpread":0,"rewardsMinSize":0,"rfqEnabled":false,"secondsDelay":0,"sentDiscord":false,"slug":"nba-who-will-win-heat-vs-warriors-scheduled-for-october-27-1000-pm-et","spread":1,"submitted_by":"0x281777D3bdD096d302791F94A2E429bb98474227","umaEndDate":"January 1, 2023","umaEndDateIso":"2023-01-01","umaResolutionStatuses":"[]","updatedAt":"2023-01-31T18:27:54.418Z","updatedBy":15,"volume":"103.499804","volume1mo":0,"volume1moAmm":0,"volume1moClob":0,"volume1wk":0,"volume1wkAmm":0,"volume1wkClob":0,"volume1yr":0,"volume1yrAmm":0,"volume1yrClob":0,"volume24hr":0,"volumeNum":103.5,"wideFormat":true},{"active":true,"approved":true,"archived":false,"bestAsk":1,"bestBid":0,"clearBookOnStart":true,"clobTokenIds":"[\"82418348624559068989631636090360708779990053875494282860793340709943733484122\", \"13805883191610852891885856689637631407157595405792251931890242806274912912618\"]","closed":true,"closedTime":"2022-10-30 06:15:33+00","commentsEnabled":false,"competitive":0,"conditionId":"0x9607f019421fbd419e28bb774d27afa3fffd6fe21ff3b5416b77c85a73210b04","createdAt":"2022-10-25T18:27:05.655Z","creator":"","cyom":false,"deploying":false,"description":"In the upcoming NBA game, scheduled for October 28:\n\nIf the Indiana Pacers win, the market will resolve to “Pacers”. \n\nIf the Washington Wizards win, the market will resolve to “Wizards”. \n\nIf the game is not completed by November 5, 2022 (11:59:59 PM ET), the market will resolve 50-50.","enableOrderBook":false,"endDate":"2022-10-28T00:00:00Z","endDateIso":"2022-10-28","featured":false,"fee":"10000000000000000","feesEnabled":false,"fpmmLive":true,"funded":false,"groupItemThreshold":"4","groupItemTitle":"Friday: Pacers vs. Wizards","hasReviewedDates":true,"holdingRewardsEnabled":false,"icon":"https://polymarket-upload.s3.us-east-2.amazonaws.com/nba.png","id":"247758","image":"https://polymarket-upload.s3.us-east-2.amazonaws.com/nba.png","lastTradePrice":0,"liquidity":"20.005034","liquidityNum":20.01,"manualActivation":false,"marketGroup":608,"marketMakerAddress":"0xBf80566b4E7ceA5aEC2de5AdF06e5395CCe457f1","marketType":"normal","negRiskOther":false,"new":false,"oneDayPriceChange":0,"oneHourPriceChange":0,"oneMonthPriceChange":0,"oneWeekPriceChange":0,"oneYearPriceChange":0,"outcomePrices":"[\"0.9999986902086395302448428797001524\", \"0.000001309791360469755157120299847641968\"]","outcomes":"[\"Pacers\", \"Wizards\"]","pagerDutyNotificationEnabled":false,"pendingDeployment":false,"question":"NBA: Who will win Pacers vs. Wizards, scheduled for October 28 (7:30 PM ET)?","questionID":"0xbc05ea146ae02b246e751e8025ce9e79fea7840ebc6f2bf08eea32533ec9e450","ready":false,"readyForCron":true,"requiresTranslation":false,"resolutionSource":"https://www.nba.com/games","resolvedBy":"0xCB1822859cEF82Cd2Eb4E6276C7916e692995130","restricted":true,"rewardsMaxSpread":0,"rewardsMinSize":0,"rfqEnabled":false,"secondsDelay":0,"sentDiscord":false,"slug":"nba-who-will-win-pacers-vs-wizards-scheduled-for-october-28-730-pm-et","spread":1,"submitted_by":"0x281777D3bdD096d302791F94A2E429bb98474227","umaEndDate":"January 1, 2023","umaEndDateIso":"2023-01-01","umaResolutionStatuses":"[]","updatedAt":"2023-01-31T20:26:40.358Z","updatedBy":15,"volume":"344.300221","volume1mo":0,"volume1moAmm":0,"volume1moClob":0,"volume1wk":0,"volume1wkAmm":0,"volume1wkClob":0,"volume1yr":0,"volume1yrAmm":0,"volume1yrClob":0,"volume24hr":0,"volumeNum":344.3,"wideFormat":true},{"active":true,"approved":true,"archived":false,"bestAsk":1,"bestBid":0,"clearBookOnStart":true,"clobTokenIds":"[\"77960858085204280811612837274519275432837593004352825281346444631942978090683\", \"10970649958023501622129088361138115127244081362786282745185485733981641776982\"]","closed":true,"closedTime":"2022-10-30 06:45:34+00","commentsEnabled":false,"competitive":0,"conditionId":"0xd47741043a94234071046453a7eba8d4755454349471f92053a44f767b196f30","createdAt":"2022-10-25T18:37:57.753Z","creator":"","cyom":false,"deploying":false,"description":"In the upcoming NBA game, scheduled for October 29:\n\nIf the Philadelphia 76ers win, the market will resolve to “76ers”. \n\nIf the Chicago Bulls win, the market will resolve to “Bulls”. \n\nIf the game is not completed by November 5, 2022 (11:59:59 PM ET), the market will resolve 50-50.","enableOrderBook":false,"endDate":"2022-10-29T00:00:00Z","endDateIso":"2022-10-29","featured":false,"fee":"10000000000000000","feesEnabled":false,"fpmmLive":true,"funded":false,"groupItemThreshold":"5","groupItemTitle":"Saturday: 76ers vs. Bulls","hasReviewedDates":true,"holdingRewardsEnabled":false,"icon":"https://polymarket-upload.s3.us-east-2.amazonaws.com/nba.png","id":"247759","image":"https://polymarket-upload.s3.us-east-2.amazonaws.com/nba.png","lastTradePrice":0,"liquidity":"20.005014","liquidityNum":20.01,"manualActivation":false,"marketGroup":608,"marketMakerAddress":"0x721FdB6601a525FfDf7F67860081954a1aF3c941","marketType":"normal","negRiskOther":false,"new":false,"oneDayPriceChange":0,"oneHourPriceChange":0,"oneMonthPriceChange":0,"oneWeekPriceChange":0,"oneYearPriceChange":0,"outcomePrices":"[\"0.9999993858874964299206946947002461\", \"0.0000006141125035700793053052997538992344\"]","outcomes":"[\"76ers\", \"Bulls\"]","pagerDutyNotificationEnabled":false,"pendingDeployment":false,"question":"NBA: Who will win 76ers vs. Bulls, scheduled for October 29 (8:00 PM ET)?","questionID":"0x16fc708eae986b60dc3b26d86c54df7c97237024cedb7a81943c4ca83743a536","ready":false,"readyForCron":true,"requiresTranslation":false,"resolutionSource":"https://www.nba.com/games","resolvedBy":"0xCB1822859cEF82Cd2Eb4E6276C7916e692995130","restricted":true,"rewardsMaxSpread":0,"rewardsMinSize":0,"rfqEnabled":false,"secondsDelay":0,"sentDiscord":false,"slug":"nba-who-will-win-76ers-vs-bulls-scheduled-for-october-29-800-pm-et","spread":1,"submitted_by":"0x281777D3bdD096d302791F94A2E429bb98474227","umaEndDate":"January 1, 2023","umaEndDateIso":"2023-01-01","umaResolutionStatuses":"[]","updatedAt":"2023-01-31T21:23:28.708Z","updatedBy":15,"volume":"170.320241","volume1mo":0,"volume1moAmm":0,"volume1moClob":0,"volume1wk":0,"volume1wkAmm":0,"volume1wkClob":0,"volume1yr":0,"volume1yrAmm":0,"volume1yrClob":0,"volume24hr":0,"volumeNum":170.32,"wideFormat":true},{"active":true,"approved":true,"archived":false,"bestAsk":1,"bestBid":0,"clearBookOnStart":true,"clobTokenIds":"[\"33689356639659248862219568481084408242609655182363717858156959867945606091260\", \"55089988681332741684714929189772285004865475010837585424089651959597444621956\"]","closed":true,"closedTime":"2022-10-31 04:45:34+00","commentsEnabled":false,"competitive":0,"conditionId":"0xd785264907eef62eed11f3a3d41b0db29d40ef5f46be583cd80414d2fab84814","createdAt":"2022-10-25T18:43:14.983Z","creator":"","cyom":false,"deploying":false,"description":"In the upcoming NBA game, scheduled for October 30:\n\nIf the New York Knicks win, the market will resolve to “Knicks”. \n\nIf the Cleveland Cavaliers win, the market will resolve to “Cavaliers”. \n\nIf the game is not completed by November 6, 2022 (11:59:59 PM ET), the market will resolve 50-50.","enableOrderBook":false,"endDate":"2022-10-30T00:00:00Z","endDateIso":"2022-10-30","featured":false,"fee":"10000000000000000","feesEnabled":false,"fpmmLive":true,"funded":false,"groupItemThreshold":"6","groupItemTitle":"Sunday: Knicks vs. Cavaliers","hasReviewedDates":true,"holdingRewardsEnabled":false,"icon":"https://polymarket-upload.s3.us-east-2.amazonaws.com/nba.png","id":"247760","image":"https://polymarket-upload.s3.us-east-2.amazonaws.com/nba.png","lastTradePrice":0,"liquidity":"20.005017","liquidityNum":20.01,"manualActivation":false,"marketGroup":608,"marketMakerAddress":"0x5Ad36C08Ad9b03566D14532C1444CfD3C498C881","marketType":"normal","negRiskOther":false,"new":false,"oneDayPriceChange":0,"oneHourPriceChange":0,"oneMonthPriceChange":0,"oneWeekPriceChange":0,"oneYearPriceChange":0,"outcomePrices":"[\"0.00000139441373279466301888396204759632\", \"0.9999986055862672053369811160379524\"]","outcomes":"[\"Knicks\", \"Cavaliers\"]","pagerDutyNotificationEnabled":false,"pendingDeployment":false,"question":"NBA: Who will win Knicks vs. Cavaliers, scheduled for October 30 (6:00 PM ET)?","questionID":"0x89acaad53c0f5694415f33c0ccdfb0cf0700fc2da1e3d3d6b48f021a3fd2b028","ready":false,"readyForCron":true,"requiresTranslation":false,"resolutionSource":"https://www.nba.com/games","resolvedBy":"0xCB1822859cEF82Cd2Eb4E6276C7916e692995130","restricted":true,"rewardsMaxSpread":0,"rewardsMinSize":0,"rfqEnabled":false,"secondsDelay":0,"sentDiscord":false,"slug":"nba-who-will-win-knicks-vs-cavaliers-scheduled-for-october-30-600-pm-et","spread":1,"submitted_by":"0x281777D3bdD096d302791F94A2E429bb98474227","umaEndDate":"January 1, 2023","umaEndDateIso":"2023-01-01","umaResolutionStatuses":"[]","updatedAt":"2023-01-31T18:53:28.892Z","updatedBy":15,"volume":"164.425561","volume1mo":0,"volume1moAmm":0,"volume1moClob":0,"volume1wk":0,"volume1wkAmm":0,"volume1wkClob":0,"volume1yr":0,"volume1yrAmm":0,"volume1yrClob":0,"volume24hr":0,"volumeNum":164.43,"wideFormat":true}],"negRiskAugmented":false,"new":false,"openInterest":0,"pendingDeployment":false,"published_at":"2022-10-25 18:51:33.593+00","requiresTranslation":false,"resolutionSource":"https://www.nba.com/games","restricted":true,"series":[{"active":true,"archived":false,"closed":false,"commentCount":6279,"commentsEnabled":false,"competitive":"0","createdAt":"2022-10-13T00:36:01.131Z","createdBy":"15","featured":false,"icon":"https://polymarket-upload.s3.us-east-2.amazonaws.com/super+cool+basketball+in+red+and+blue+wow.png","id":"2","image":"https://polymarket-upload.s3.us-east-2.amazonaws.com/super+cool+basketball+in+red+and+blue+wow.png","layout":"default","new":false,"publishedAt":"2023-01-30 17:13:39.006+00","recurrence":"daily","requiresTranslation":false,"restricted":true,"seriesType":"single","slug":"nba","startDate":"2021-01-01T17:00:00Z","ticker":"nba","title":"NBA","updatedAt":"2026-01-06T13:28:31.721571Z","updatedBy":"15","volume24hr":0}],"seriesSlug":"nba","showAllOutcomes":false,"showMarketImages":true,"slug":"nba-week-2","sortBy":"ascending","startDate":"2022-10-25T00:00:00Z","tags":[{"forceShow":false,"id":"100215","label":"All","requiresTranslation":false,"slug":"all","updatedAt":"2025-12-18T03:27:54.040735Z"}],"ticker":"nba-week-2","title":"NBA: Week 2","updatedAt":"2024-03-22T01:57:13.897025Z","volume":832.56,"volume1mo":0,"volume1wk":0,"volume1yr":0,"volume24hr":0}