{
  "entity": "event",
  "event_id": "5722",
  "folder_rule": "event.createdAt (fallback: max(markets[].published_at))",
  "folder_dt_utc": "2022-07-27T14:43:35.512000Z",
  "event_createdAt": "2022-07-27T14:43:35.512Z",
  "event_creationDate": "2022-04-18T00:00:00Z",
  "event_startDate": "2022-04-18T00:00:00Z",
  "event_endDate": "2022-04-18T00:00:00Z",
  "event_updatedAt": "2024-04-22T21:21:19.666706Z",
  "markets_len": 3,
  "market_ids": [
    "243390",
    "243392",
    "243394"
  ],
  "series_len": 1,
  "series_ids": [
    "4"
  ],
  "series_slug": "nhl"
}