{
  "entity": "market",
  "market_id": "224611",
  "folder_rule": "market.createdAt (fallback: market.published_at)",
  "folder_dt_utc": "2021-07-19T22:05:01.171000Z",
  "market_createdAt": "2021-07-19T22:05:01.171Z",
  "market_updatedAt": "2024-04-23T00:56:52.916393Z",
  "market_startDate": null,
  "market_endDate": "2021-08-08T00:00:00Z",
  "market_closedTime": "2021-08-08 17:55:04+00",
  "conditionId": "0xbecd261b87c50229e39db4cfeebc950e86378af638de60abda5bffb7a6035866",
  "slug": "will-the-us-mens-basketball-team-win-the-gold-medal-at-the-2020-olympics",
  "question": "Will the U.S. Men’s Basketball team win the Gold Medal at the 2020 Olympics?"
}