{
  "entity": "market",
  "market_id": "241389",
  "folder_rule": "market.createdAt (fallback: market.published_at)",
  "folder_dt_utc": "2022-02-09T10:51:59.666000Z",
  "market_createdAt": "2022-02-09T10:51:59.666Z",
  "market_updatedAt": "2024-04-23T00:08:20.431533Z",
  "market_startDate": "2022-02-09T17:26:15.706Z",
  "market_endDate": "2022-02-09T00:00:00Z",
  "market_closedTime": "2022-02-11 07:14:05+00",
  "conditionId": "0x2b4e33b7be2d4b92501b92499131df7b230101a425b525176e59750ee468ea76",
  "slug": "nhl-will-the-oilers-beat-the-blackhawks-by-more-than-1p5-goals-in-their-february-9-matchup-8-pm-et",
  "question": "NHL: Will the Oilers beat the Blackhawks by more than 1.5 goals in their February 9 matchup (8 PM ET)?"
}